abox/__init__.py
abox/playground/__init__.py
abox/playground/hello_world.py
abox-0.0.0.dist-info/LICENSE
abox-0.0.0.dist-info/METADATA
abox-0.0.0.dist-info/WHEEL
abox-0.0.0.dist-info/entry_points.txt
abox-0.0.0.dist-info/top_level.txt
abox-0.0.0.dist-info/RECORD
