Metadata-Version: 2.1
Name: abox
Version: 0.0.0
Summary: WIP
Home-page: UNKNOWN
Author: abox-team
License: see file
Platform: UNKNOWN
Classifier: Development Status :: 1 - Planning
Classifier: Intended Audience :: Developers
Classifier: Operating System :: Unix
Classifier: Operating System :: POSIX
Classifier: Operating System :: Microsoft :: Windows
Classifier: Programming Language :: Python
Classifier: Programming Language :: Python :: 3 :: Only
Classifier: Programming Language :: Python :: 3.6
Classifier: Programming Language :: Python :: 3.7
Classifier: Topic :: Utilities
Requires-Python: >=3.6
Provides-Extra: dev
Requires-Dist: black (==20.8b1) ; extra == 'dev'
Requires-Dist: bump2version (>=1.0.0) ; extra == 'dev'
Requires-Dist: coverage (==5.0) ; extra == 'dev'
Requires-Dist: isort (==5.7.0) ; extra == 'dev'
Requires-Dist: pre-commit (>=2.10.1) ; extra == 'dev'
Requires-Dist: pytest (>=4.0) ; extra == 'dev'
Requires-Dist: pytest-cov (~=2.10.1) ; extra == 'dev'
Requires-Dist: tox (>=3.22.0) ; extra == 'dev'
Requires-Dist: twine (>=3.3.0) ; extra == 'dev'
